LICENSE
README.md
setup.py
aapyt/__init__.py
aapyt/aapyt.py
aapyt.egg-info/PKG-INFO
aapyt.egg-info/SOURCES.txt
aapyt.egg-info/dependency_links.txt
aapyt.egg-info/top_level.txt