Metadata-Version: 2.1
Name: aapyt
Version: 0.1.2
Summary: Python wrapper for aapt
Home-page: UNKNOWN
Author: David Lev
Author-email: davidlev@telegmail.com
License: MIT
Download-URL: https://pypi.org/project/aapyt/
Project-URL: Documentation, https://github.com/david-lev/aapyt#readme
Project-URL: Issue Tracker, https://github.com/david-lev/aapyt/issues
Project-URL: Source Code, https://github.com/david-lev/aapyt
Platform: UNKNOWN
License-File: LICENSE
